{"1BQgQVhhydqWjQ/JIGBVBQ==":"tracker%20editan-554x554.jpg","/Vo+XD40N2w4fiOFCSrbJw==":"contoh-554x554.png","TlPJ4HhCVCIpk5COPFVM7A==":"tracker-267x189.jpg","GzTHv0aqmAEYX1ZG8vM9Rw==":"forest%20green%20photo%20simple%20memo%20(1)-1414x2000.png","HpyEGFYJhfsi8uEawZbBNg==":"desain%20tanpa%20judul-1920x1920.png","O+gFFhGrJd4Ljk12C6qnrg==":"mount%20traker%202-4501x4501.png","lD2WF8oVK/S9eKMbijHMqg==":"mbr-955x1080.jpg","Bu6yZB7QG/t8Tu8kqUdcaw==":"mbr-720x1080.jpg","NoLQGuQTrUrumGhsXcHzbA==":"mbr-1620x1080.jpg"}